{"paths":{"0":["effect_txz_get",3],"1":["ui_afArenaBattlePass",5],"2":["txz_xzl_banner2",4],"3":["effect_tip_signin",1],"4":["txz_xzl_banner2",3],"5":["effect_tip_signin",3],"6":["effect_txz_get",4],"7":["effect_tip_signin",4],"8":["effect_txz_get",1],"9":["ui_afArenaBattlePass_atlas0",4],"10":["txz_xzl_banner2",1],"11":["effect_tip_signin",2,1],"12":["ActBattlePassItem",0],"13":["ui_afArenaBattlePass_atlas0",2,1],"14":["txz_xzl_banner2",2,1],"15":["effect_txz_get",2,1]},"types":["cc.TextAsset","sp.SkeletonData","cc.SpriteFrame","cc.Asset","cc.Texture2D","cc.BufferAsset"],"uuids":["13Hsn6X/9G+4i10mwa9AH+","3aJH9iqSFD6I0d1EwUptZs","3eE7OQ8+hPOr75maJgjgEn","4abZNyTd9LH4nsLZOcI1+F","4bYhc91klH3aXuX3/Mf18t","5a5rP8GzVGyooIwePbuIKW","5cv+c4QqRHAqJja+KcQ8tv","9eVkX24/JL7Krc+KuPcGWW","cf0kmAvNdAOZVsP1tQDKwI","ebys3RFixOgbUdRZLZBOP3","f9pOhTUdxAUr5Jo5xLO6vp","4fUoZqR5pDHbuGDs55Bnf1","5eWvPGRVBFuLK92/aWRqOJ","aeaF2MbCZAsYgcTA/2zsA0","f0g5AfqiFEbaNurZzF2ymY","favr2DeItHvKqnOuHbS1UU"],"scenes":{},"redirect":[],"deps":[],"packs":{"0fe84e7a7":[2,6,7,9]},"name":"ui_afArenaBattlePass","importBase":"import","nativeBase":"native","debug":false,"isZip":false,"encrypted":false,"versions":{"import":["0fe84e7a7","8ff53",0,"6197e",1,"552e6",3,"11dc7",4,"55866",11,"0f75f",5,"211c7",12,"0da3f",13,"ac863",8,"2566f",14,"e8801",10,"83906",15,"d0fb3"],"native":[0,"2e46c",1,"134e2",2,"7686d",3,"0cafe",4,"82452",5,"3e115",6,"05f33",7,"6486a",8,"3f7c5",9,"91fd6",10,"daa21"]}}